[{"model": "habits.habit", "pk": 1, "fields": {"user": 6, "place": "Republican", "time": "18:07:00", "action": "Represent bit voice.", "is_pleasant_habit": true, "related_habit": null, "frequency": 3, "reward": "by", "estimated_time": 6, "is_public": true, "last_action_datetime": "2024-01-18T18:40:56.761Z"}}, {"model": "habits.habit", "pk": 2, "fields": {"user": 12, "place": "song", "time": "12:00:00", "action": "Church sign law street human management.", "is_pleasant_habit": false, "related_habit": null, "frequency": 4, "reward": "dark", "estimated_time": 38, "is_public": true, "last_action_datetime": "2024-01-18T18:40:56.761Z"}}, {"model": "habits.habit", "pk": 3, "fields": {"user": 9, "place": "question", "time": "16:02:00", "action": "Near realize language our he.", "is_pleasant_habit": false, "related_habit": null, "frequency": 2, "reward": "fly", "estimated_time": 38, "is_public": true, "last_action_datetime": "2024-01-18T18:40:56.761Z"}}, {"model": "habits.habit", "pk": 4, "fields": {"user": 9, "place": "major", "time": "11:16:00", "action": "Able return continue beyond point least side.", "is_pleasant_habit": true, "related_habit": null, "frequency": 1, "reward": "billion", "estimated_time": 40, "is_public": false, "last_action_datetime": "2024-01-18T18:40:56.761Z"}}, {"model": "habits.habit", "pk": 5, "fields": {"user": 9, "place": "write", "time": "11:01:00", "action": "Both Mr someone culture more manager.", "is_pleasant_habit": true, "related_habit": null, "frequency": 7, "reward": "tell", "estimated_time": 1, "is_public": false, "last_action_datetime": "2024-01-18T18:40:56.761Z"}}, {"model": "habits.habit", "pk": 6, "fields": {"user": 8, "place": "impact", "time": "21:56:00", "action": "Scene security method.", "is_pleasant_habit": true, "related_habit": null, "frequency": 7, "reward": "major", "estimated_time": 33, "is_public": true, "last_action_datetime": "2024-01-18T18:40:56.761Z"}}, {"model": "habits.habit", "pk": 7, "fields": {"user": 12, "place": "senior", "time": "17:25:00", "action": "Bill similar inside join father business.", "is_pleasant_habit": true, "related_habit": null, "frequency": 6, "reward": "beautiful", "estimated_time": 28, "is_public": true, "last_action_datetime": "2024-01-18T18:40:56.761Z"}}, {"model": "habits.habit", "pk": 8, "fields": {"user": 3, "place": "usually", "time": "13:42:00", "action": "Machine floor form wife ready law event.", "is_pleasant_habit": false, "related_habit": null, "frequency": 5, "reward": "structure", "estimated_time": 52, "is_public": true, "last_action_datetime": "2024-01-18T18:40:56.761Z"}}, {"model": "habits.habit", "pk": 9, "fields": {"user": 10, "place": "wife", "time": "15:09:00", "action": "Guess less station nothing recently and mother.", "is_pleasant_habit": false, "related_habit": null, "frequency": 4, "reward": "citizen", "estimated_time": 54, "is_public": true, "last_action_datetime": "2024-01-18T18:40:56.761Z"}}, {"model": "habits.habit", "pk": 10, "fields": {"user": 6, "place": "customer", "time": "15:13:00", "action": "Help oil life performance.", "is_pleasant_habit": true, "related_habit": null, "frequency": 4, "reward": "gun", "estimated_time": 34, "is_public": true, "last_action_datetime": "2024-01-18T18:40:56.761Z"}}, {"model": "habits.habit", "pk": 11, "fields": {"user": 12, "place": "cultural", "time": "17:31:00", "action": "Politics modern everyone purpose far.", "is_pleasant_habit": true, "related_habit": null, "frequency": 4, "reward": "avoid", "estimated_time": 30, "is_public": true, "last_action_datetime": "2024-01-18T18:40:56.761Z"}}, {"model": "habits.habit", "pk": 12, "fields": {"user": 11, "place": "but", "time": "20:05:00", "action": "Particularly light gun fine hotel picture discover.", "is_pleasant_habit": false, "related_habit": null, "frequency": 1, "reward": "analysis", "estimated_time": 5, "is_public": true, "last_action_datetime": "2024-01-18T18:40:56.761Z"}}, {"model": "habits.habit", "pk": 13, "fields": {"user": 3, "place": "measure", "time": "18:18:00", "action": "Operation sometimes break economy race which first.", "is_pleasant_habit": false, "related_habit": null, "frequency": 6, "reward": "view", "estimated_time": 52, "is_public": true, "last_action_datetime": "2024-01-18T18:40:56.761Z"}}, {"model": "habits.habit", "pk": 14, "fields": {"user": 9, "place": "explain", "time": "15:53:00", "action": "Woman feeling lot.", "is_pleasant_habit": true, "related_habit": null, "frequency": 3, "reward": "white", "estimated_time": 29, "is_public": true, "last_action_datetime": "2024-01-18T18:40:56.761Z"}}, {"model": "habits.habit", "pk": 15, "fields": {"user": 12, "place": "program", "time": "17:02:00", "action": "Network rise open whose program own.", "is_pleasant_habit": true, "related_habit": null, "frequency": 6, "reward": "national", "estimated_time": 18, "is_public": false, "last_action_datetime": "2024-01-18T18:40:56.761Z"}}, {"model": "habits.habit", "pk": 16, "fields": {"user": 4, "place": "once", "time": "13:29:00", "action": "Show another show whether affect week make.", "is_pleasant_habit": false, "related_habit": null, "frequency": 1, "reward": "too", "estimated_time": 14, "is_public": false, "last_action_datetime": "2024-01-18T18:40:56.761Z"}}, {"model": "habits.habit", "pk": 17, "fields": {"user": 7, "place": "nothing", "time": "10:38:00", "action": "Manager phone party create.", "is_pleasant_habit": true, "related_habit": null, "frequency": 1, "reward": "cause", "estimated_time": 24, "is_public": true, "last_action_datetime": "2024-01-18T18:40:56.761Z"}}, {"model": "habits.habit", "pk": 18, "fields": {"user": 6, "place": "plan", "time": "20:06:00", "action": "Culture marriage blue.", "is_pleasant_habit": true, "related_habit": null, "frequency": 6, "reward": "director", "estimated_time": 17, "is_public": false, "last_action_datetime": "2024-01-18T18:40:56.761Z"}}, {"model": "habits.habit", "pk": 19, "fields": {"user": 5, "place": "face", "time": "19:08:00", "action": "Black myself shake natural employee might adult.", "is_pleasant_habit": true, "related_habit": null, "frequency": 1, "reward": "throughout", "estimated_time": 59, "is_public": false, "last_action_datetime": "2024-01-18T18:40:56.761Z"}}, {"model": "habits.habit", "pk": 20, "fields": {"user": 8, "place": "science", "time": "16:48:00", "action": "Investment bag billion.", "is_pleasant_habit": true, "related_habit": null, "frequency": 7, "reward": "although", "estimated_time": 30, "is_public": true, "last_action_datetime": "2024-01-18T18:40:56.761Z"}}, {"model": "habits.habit", "pk": 21, "fields": {"user": 11, "place": "fish", "time": "15:31:00", "action": "Cell cup factor return each fish rest hotel.", "is_pleasant_habit": false, "related_habit": null, "frequency": 4, "reward": "machine", "estimated_time": 54, "is_public": false, "last_action_datetime": "2024-01-18T18:40:56.761Z"}}, {"model": "habits.habit", "pk": 22, "fields": {"user": 6, "place": "fear", "time": "19:20:00", "action": "Issue send whole him major.", "is_pleasant_habit": false, "related_habit": null, "frequency": 6, "reward": "else", "estimated_time": 12, "is_public": false, "last_action_datetime": "2024-01-18T18:40:56.761Z"}}, {"model": "habits.habit", "pk": 23, "fields": {"user": 5, "place": "TV", "time": "12:26:00", "action": "High modern control stock minute picture open.", "is_pleasant_habit": true, "related_habit": null, "frequency": 6, "reward": "without", "estimated_time": 40, "is_public": false, "last_action_datetime": "2024-01-18T18:40:56.761Z"}}, {"model": "habits.habit", "pk": 24, "fields": {"user": 4, "place": "sport", "time": "10:00:00", "action": "Important natural especially yet so understand.", "is_pleasant_habit": false, "related_habit": null, "frequency": 7, "reward": "kind", "estimated_time": 8, "is_public": false, "last_action_datetime": "2024-01-18T18:40:56.761Z"}}, {"model": "habits.habit", "pk": 25, "fields": {"user": 8, "place": "under", "time": "18:02:00", "action": "Kid others specific toward then reduce.", "is_pleasant_habit": false, "related_habit": null, "frequency": 2, "reward": "read", "estimated_time": 10, "is_public": false, "last_action_datetime": "2024-01-18T18:40:56.761Z"}}, {"model": "habits.habit", "pk": 26, "fields": {"user": 3, "place": "hot", "time": "18:01:00", "action": "As lose else.", "is_pleasant_habit": true, "related_habit": null, "frequency": 2, "reward": "yeah", "estimated_time": 25, "is_public": false, "last_action_datetime": "2024-01-18T18:40:56.761Z"}}, {"model": "habits.habit", "pk": 27, "fields": {"user": 3, "place": "in", "time": "20:34:00", "action": "Heart my popular head break Congress cultural.", "is_pleasant_habit": false, "related_habit": null, "frequency": 3, "reward": "since", "estimated_time": 45, "is_public": true, "last_action_datetime": "2024-01-18T18:40:56.761Z"}}, {"model": "habits.habit", "pk": 28, "fields": {"user": 4, "place": "different", "time": "13:44:00", "action": "Month evening decision kid artist less.", "is_pleasant_habit": false, "related_habit": null, "frequency": 3, "reward": "goal", "estimated_time": 44, "is_public": false, "last_action_datetime": "2024-01-18T18:40:56.761Z"}}, {"model": "habits.habit", "pk": 29, "fields": {"user": 4, "place": "economy", "time": "14:42:00", "action": "Station source resource.", "is_pleasant_habit": false, "related_habit": null, "frequency": 6, "reward": "radio", "estimated_time": 38, "is_public": false, "last_action_datetime": "2024-01-18T18:40:56.761Z"}}, {"model": "habits.habit", "pk": 30, "fields": {"user": 12, "place": "hundred", "time": "17:41:00", "action": "Check father positive great.", "is_pleasant_habit": true, "related_habit": null, "frequency": 5, "reward": "late", "estimated_time": 53, "is_public": true, "last_action_datetime": "2024-01-18T18:40:56.761Z"}}]